mf4parser.py
mf4parser-1.2.dist-info/LICENSE
mf4parser-1.2.dist-info/METADATA
mf4parser-1.2.dist-info/WHEEL
mf4parser-1.2.dist-info/top_level.txt
mf4parser-1.2.dist-info/RECORD
