Metadata-Version: 2.1
Name: mf4parser
Version: 1.2
Summary: A Python package to extract signals from MDF4 files.
Home-page: https://github.com/sridhar-eswaran/mf4-parser.git
Author: Sridhar Eswaran
Author-email: mail2sridhare@gmail.com
License: GNU GPLv3
Platform: UNKNOWN
Classifier: License :: OSI Approved :: GNU General Public License v3 (GPLv3)
Classifier: Programming Language :: Python :: 3
Classifier: Programming Language :: Python :: 3.6
Classifier: Programming Language :: Python :: 3.7
Classifier: Programming Language :: Python :: 3.8
Classifier: Programming Language :: Python :: 3.9
Classifier: Operating System :: OS Independent
Requires-Dist: asammdf
Requires-Dist: pandas
Requires-Dist: numpy
Requires-Dist: pyexcel-xlsx
Requires-Dist: pyexcel-xls
Requires-Dist: pyyaml
Requires-Dist: xlrd
Requires-Dist: xlsx
Requires-Dist: xlsxwriter
